MANIFEST.in
README.md
build.py
pyproject.toml
requirements-dev.txt
requirements.txt
setup.py
auto_screener/base.py
auto_screener/collect.py
auto_screener/dataset.py
auto_screener/document.py
auto_screener/exchanges.py
auto_screener/feed.py
auto_screener/hints.py
auto_screener/interval.py
auto_screener/screener.py
auto_screener/screening.py
auto_screener/symbols.py
auto_screener.egg-info/PKG-INFO
auto_screener.egg-info/SOURCES.txt
auto_screener.egg-info/dependency_links.txt
auto_screener.egg-info/requires.txt
auto_screener.egg-info/top_level.txt